CHANGES.rst
LICENSE
MANIFEST.in
README.rst
requirements-dev.txt
requirements.txt
setup.cfg
setup.py
mactopeer.egg-info/PKG-INFO
mactopeer.egg-info/SOURCES.txt
mactopeer.egg-info/dependency_links.txt
mactopeer.egg-info/namespace_packages.txt
mactopeer.egg-info/requires.txt
mactopeer.egg-info/top_level.txt
pierky/__init__.py
pierky/mactopeer/__init__.py
pierky/mactopeer/cli.py
pierky/mactopeer/errors.py
pierky/mactopeer/version.py
scripts/mactopeer
tests/conftest.py
tests/test_cli.py
tests/test_lib.py
tests/devices/bad.json
tests/devices/duplicate.json
tests/devices/missing_hostname.json
tests/devices/missing_vendor.json
tests/devices/working1.json
tests/devices/expected/from_cli.expected.json
tests/devices/expected/from_cli.expected_with_args_from_cli.json
tests/devices/expected/working1.expected.json
tests/devices/expected/working1.expected_with_optargs.json
tests/devices/expected/working1.expected_with_pass.json
tests/devices/expected/working1.expected_with_pass_and_user.json
tests/filters/mac
tests/mocked_data/3_devices/expected_results.asn_filter.json
tests/mocked_data/3_devices/expected_results.asn_filter.pmacct
tests/mocked_data/3_devices/expected_results.ip_filter.json
tests/mocked_data/3_devices/expected_results.ip_filter.pmacct
tests/mocked_data/3_devices/expected_results.json
tests/mocked_data/3_devices/expected_results.mac_filter.json
tests/mocked_data/3_devices/expected_results.mac_filter.pmacct
tests/mocked_data/3_devices/expected_results.pmacct
tests/mocked_data/3_devices/expected_results.prefix_filter.json
tests/mocked_data/3_devices/expected_results.prefix_filter.pmacct
tests/mocked_data/3_devices/router1/get_arp_table.1
tests/mocked_data/3_devices/router1/get_bgp_neighbors.1
tests/mocked_data/3_devices/router2/get_arp_table.1
tests/mocked_data/3_devices/router2/get_bgp_neighbors.1
tests/mocked_data/3_devices/router3/get_arp_table.1
tests/mocked_data/3_devices/router3/get_bgp_neighbors.1
tests/mocked_data/more_mac/expected_results.json
tests/mocked_data/more_mac/expected_results.pmacct
tests/mocked_data/more_mac/router1/get_arp_table.1
tests/mocked_data/more_mac/router1/get_bgp_neighbors.1
tests/mocked_data/pdb_live/expected_results.json
