Metadata-Version: 1.1
Name: mactopeer
Version: 0.3.0
Summary: Automatically fetch MAC/IP address tables (ARP and IPv6 neighbors) from devices and build MAC address to BGP peer ASN mappings.
Home-page: https://github.com/pierky/mactopeer
Author: Pier Carlo Chiodi
Author-email: pierky@pierky.com
License: GPLv3
Download-URL: https://github.com/pierky/mactopeer
Keywords: BGP,IP Routing,pmacct,bgp_peer_src_as_map
Platform: UNKNOWN
Classifier: Development Status :: 4 - Beta
Classifier: Environment :: Console
Classifier: Intended Audience :: Information Technology
Classifier: Intended Audience :: System Administrators
Classifier: Intended Audience :: Telecommunications Industry
Classifier: License :: OSI Approved :: GNU General Public License v3 (GPLv3)
Classifier: Operating System :: POSIX
Classifier: Operating System :: Unix
Classifier: Programming Language :: Python
Classifier: Programming Language :: Python :: 2.7
Classifier: Programming Language :: Python :: 3.4
Classifier: Topic :: Internet :: WWW/HTTP
Classifier: Topic :: System :: Networking
